ovos_translate_plugin_deepl/__init__.py
ovos_translate_plugin_deepl/version.py
ovos_translate_plugin_deepl-0.0.0.dist-info/LICENSE
ovos_translate_plugin_deepl-0.0.0.dist-info/METADATA
ovos_translate_plugin_deepl-0.0.0.dist-info/WHEEL
ovos_translate_plugin_deepl-0.0.0.dist-info/entry_points.txt
ovos_translate_plugin_deepl-0.0.0.dist-info/top_level.txt
ovos_translate_plugin_deepl-0.0.0.dist-info/RECORD
