Metadata-Version: 2.1
Name: ovos-translate-plugin-deepl
Version: 0.0.0
Summary: OVOS translation/detection module wrapping deepl-python
Home-page: https://github.com/emphasize/ovos-translate-plugin-deepl
Author: emphasize
Author-email: UNKNOWN
License: Apache-2.0
Platform: UNKNOWN
Classifier: Development Status :: 3 - Alpha
Classifier: Intended Audience :: Developers
Classifier: Topic :: Text Processing :: Linguistic
Classifier: License :: OSI Approved :: Apache Software License
Classifier: Programming Language :: Python :: 3.6
Classifier: Programming Language :: Python :: 3.7
Classifier: Programming Language :: Python :: 3.8
Classifier: Programming Language :: Python :: 3.9
Classifier: Programming Language :: Python :: 3.10
Classifier: Programming Language :: Python :: 3.11
Requires-Dist: deepl
Requires-Dist: ovos-plugin-manager (>=0.0.1a2)
